solution_efe_test/__init__.py
solution_efe_test/database.py
solution_efe_test/first.py
solution_efe_test_rulman26-1.0.1.dist-info/LICENSE
solution_efe_test_rulman26-1.0.1.dist-info/METADATA
solution_efe_test_rulman26-1.0.1.dist-info/WHEEL
solution_efe_test_rulman26-1.0.1.dist-info/top_level.txt
solution_efe_test_rulman26-1.0.1.dist-info/RECORD
