Metadata-Version: 2.1
Name: solution-efe-test-rulman26
Version: 1.0.1
Summary: Paquete de test
Home-page: https://github.com/pypa/sampleproject
Author: Rulman Ferro
Author-email: rulman.ferro@tismart.com
License: UNKNOWN
Platform: UNKNOWN
Classifier: Programming Language :: Python :: 3
Classifier: License :: OSI Approved :: MIT License
Classifier: Operating System :: OS Independent
Requires-Python: >=3.6
Requires-Dist: pymysql
